heureka/__init__.py
heureka/io/__init__.py
heureka/io/qap.py
heureka-0.1.1.dist-info/LICENSE
heureka-0.1.1.dist-info/WHEEL
heureka-0.1.1.dist-info/METADATA
heureka-0.1.1.dist-info/RECORD
