Metadata-Version: 2.1
Name: heureka
Version: 0.1.1
Summary: 
License: GPL-3.0
Author: max
Author-email: maxmueller89@gmail.com
Requires-Python: >=3.8,<4.0
Classifier: License :: OSI Approved :: GNU General Public License v3 (GPLv3)
Classifier: Programming Language :: Python :: 3
Classifier: Programming Language :: Python :: 3.8
Requires-Dist: numpy (>=1.18.5,<2.0.0)
